waxnftdispatcher/__init__.py
waxnftdispatcher/waxNFTdispatcher.py
waxnftdispatcher-0.3.6.dist-info/LICENSE
waxnftdispatcher-0.3.6.dist-info/METADATA
waxnftdispatcher-0.3.6.dist-info/WHEEL
waxnftdispatcher-0.3.6.dist-info/RECORD
