Metadata-Version: 2.1
Name: waxNFTdispatcher
Version: 0.3.6
Summary: This library will help you to transfer or to mint NFTs on the WAX blockchain
Home-page: https://github.com/alparo/waxNFTdispatcher
License: MIT
Author: Amparo Dios
Author-email: amparo.dios@gmail.com
Requires-Python: >=3.8.0,<4.0
Classifier: License :: OSI Approved :: MIT License
Classifier: Programming Language :: Python :: 3
Classifier: Programming Language :: Python :: 3.8
Classifier: Programming Language :: Python :: 3.9
Classifier: Programming Language :: Python :: 3.10
Classifier: Programming Language :: Python :: 3.11
Classifier: Programming Language :: Python :: 3.12
Requires-Dist: loguru (>=0.6.0,<0.7.0)
Requires-Dist: pyntelope (>=0.8.0,<0.9.0)
Requires-Dist: requests (>=2.28.1,<3.0.0)
Project-URL: Repository, https://github.com/alparo/waxNFTdispatcher
